{
  "openapi": "3.0.0",
  "info": {
    "version": "1.0.0",
    "title": "Healthflex Application",
    "description": "Healthflex Application"
  },
  "servers": [
    {
      "url": "http://localhost:8000",
      "description": "Local server"
    },
    {
      "url": "https://health-flex-assessment.onrender.com",
      "description": "Production server"
    }
  ],
  "paths": {
    "/api/v1/users/register": {
      "post": {
        "tags": [
          "User-Auth"
        ],
        "description": "",
        "responses": {
          "200": {
            "description": "OK"
          }
        },
        "requestBody": {
          "content": {
            "application/json": {
              "schema": {
                "type": "object",
                "properties": {
                  "username": {
                    "example": "any"
                  },
                  "password": {
                    "example": "any"
                  }
                }
              }
            }
          }
        }
      }
    },
    "/api/v1/users/login": {
      "post": {
        "tags": [
          "User-Auth"
        ],
        "description": "",
        "responses": {
          "200": {
            "description": "OK"
          }
        },
        "requestBody": {
          "content": {
            "application/json": {
              "schema": {
                "type": "object",
                "properties": {
                  "username": {
                    "example": "any"
                  },
                  "password": {
                    "example": "any"
                  }
                }
              }
            }
          }
        }
      }
    },
    "/api/v1/users/logout": {
      "post": {
        "tags": [
          "User-Auth"
        ],
        "description": "",
        "responses": {
          "200": {
            "description": "OK"
          }
        }
      }
    },
    "/api/v1/users/{userId}/timeline": {
      "get": {
        "tags": [
          "User"
        ],
        "description": "",
        "parameters": [
          {
            "name": "userId",
            "in": "path",
            "required": true,
            "schema": {
              "type": "string"
            }
          },
          {
            "name": "cursor",
            "in": "query",
            "schema": {
              "type": "string"
            }
          },
          {
            "name": "limit",
            "in": "query",
            "schema": {
              "type": "string"
            }
          }
        ],
        "responses": {
          "200": {
            "description": "OK"
          }
        }
      }
    },
    "/api/v1/tweets/": {
      "post": {
        "tags": [
          "Tweet"
        ],
        "description": "",
        "responses": {
          "200": {
            "description": "OK"
          }
        },
        "requestBody": {
          "content": {
            "application/json": {
              "schema": {
                "type": "object",
                "properties": {
                  "text": {
                    "example": "any"
                  }
                }
              }
            }
          }
        }
      }
    }
  }
}